Workbook

Sheet 📖 Instructions
A1: 🎯 Digital Agency Service Pricing Calculator
A2: Based on Job Costing methodology (Ms. Dawn Williams, Resilia Accounting Services)
A4: HOW TO USE THIS TOOL
A5: STEP 1 | B5: 💰 Business Costs | C5: Enter all your monthly tool subscriptions (Figma, Verpex, Adobe CC, Namecheap, Fygaro) and all other indirect monthly costs (transport, utilities, insurance, etc.).
A6: STEP 2 | B6: 👥 Team & Hours | C6: Enter each team member's hourly rate and how many hours per year they work — split between billable and non-billable hours.
A7: STEP 3 | B7: ⚙️ Overhead Rate | C7: Review the auto-calculated overhead cost per billable hour. This is the engine of your pricing — no manual entry needed.
A8: STEP 4 | B8: 🔧 Service Pricing | C8: For each service (Web Design, SEO, Ads, PM), enter the average hours each team member spends. Prices calculate automatically.
A9: STEP 5 | B9: 📊 Price Summary | C9: Your minimum selling prices appear here. Add your desired markup % and compare Job Costing vs Process Costing results.
A11: COLOUR KEY
A12: ■ | B12: Input cell — Enter your values here
A13: ■ | B13: Calculated cell — do not edit
A14: ■ | B14: Linked from another sheet — do not edit
A15: ■ | B15: Section total / key result

Sheet 💰 Business Costs
A1: 💰 Business Costs — Monthly Expenses
A2: Expense Category | B2: Item / Description | C2: Monthly Amount ($) | D2: Annual Amount ($) | E2: Notes
A3: DIRECT TOOL SUBSCRIPTIONS (costs directly tied to delivering your services)
A4: Design | B4: Figma (Professional) | C4: 40.8 | D4: =C4*12 -> 489.6 | E4: Design tool for Web & UI work
A5: Web Hosting | B5: Verpex Website Hosting | C5: 61.9 | D5: =C5*12 -> 742.8 | E5: Client & agency hosting
A6: Creative Suite | B6: Adobe Creative Cloud | C6: 61.2 | D6: =C6*12 -> 734.4 | E6: Photoshop, Illustrator, Premiere, etc.
A7: Domains | B7: Namecheap Domain Hosting | C7: 5 | D7: =C7*12 -> 60 | E7: Domain registrations & renewals (avg/mo)
A8: Payments/Mgmt | B8: Fygaro | C8: 30.58 | D8: =C8*12 -> 366.96 | E8: Invoicing & business management platform
A9: SUBTOTAL – Direct Tools | C9: =SUM(C4:C8) -> 199.48 | D9: =SUM(D4:D8) -> 2393.76
A11: INDIRECT / OVERHEAD COSTS (business expenses incurred regardless of jobs performed)
A12: Transport | B12: Fuel / Rideshare / Commuting | C12: 140 | D12: =C12*12 -> 1680 | E12: Client visits, errands, co-working travel
A13: Utilities | B13: Electricity | C13: 60 | D13: =C13*12 -> 720 | E13: Home-office or studio electricity
A14: Utilities | B14: Internet & Phone | C14: 157 | D14: =C14*12 -> 1884 | E14: Business internet + mobile plan
A15: Insurance | B15: Professional Indemnity Insurance | C15: 0 | D15: =C15*12 -> 0 | E15: Errors & omissions coverage
A16: Insurance | B16: Health Insurance | C16: 200 | D16: =C16*12 -> 2400 | E16: Personal health coverage (business portion)
A17: Office | B17: Co-working Space / Office Rent | C17: 30 | D17: =C17*12 -> 360 | E17: If applicable; set to 0 if home office
A18: Banking | B18: Bank / Payment Processing Fees | C18: 0 | D18: =C18*12 -> 0 | E18: Wire fees, Stripe/PayPal charges, etc.
A19: Marketing | B19: Agency Marketing & Ads (own brand) | C19: 500 | D19: =C19*12 -> 6000 | E19: Self-promotion spend
A20: Professional | B20: Continuing Education / Courses | C20: 0 | D20: =C20*12 -> 0 | E20: Training, certifications, webinars
A21: Professional | B21: Accounting / Bookkeeping | C21: 0 | D21: =C21*12 -> 0 | E21: Accountant or software fees
A22: Contingency | B22: Miscellaneous / Contingency (5% of above) | C22: =SUM(C12:C21)*0.05 -> 54.35 | D22: =C22*12 -> 652.2 | E22: Auto-calculated at 5%
A23: SUBTOTAL – Indirect / Overhead | C23: =SUM(C12:C22) -> 1141.35 | D23: =SUM(D12:D22) -> 13696.2
A25: ⭐ GRAND TOTAL – All Business Costs (excl. Labour) | C25: =C9+C23 -> 1340.83 | D25: =D9+D23 -> 16089.96

Sheet 👥 Team & Hours
A1: 👥 Team & Hours
A2: Role | B2: Name / Note | C2: Hourly Rate ($) | D2: Work Days/Year | E2: Daily Work Hours | F2: Billable % | G2: Annual Billable Hrs | H2: Annual Labour Cost ($)
A3: Founder / Lead Designer | B3: Owner | C3: 100 | D3: 220 | E3: 6 | F3: 0.7 | G3: =D3*E3*F3 -> 924 | H3: =G3*C3 -> 92400
A4: Developer / Coder | B4: You or contractor | C4: 120 | D4: 220 | E4: 6 | F4: 0.75 | G4: =D4*E4*F4 -> 990 | H4: =G4*C4 -> 118800
A5: Digital Marketing Mgr | B5: You or contractor | C5: 60 | D5: 220 | E5: 5 | F5: 0.8 | G5: =D5*E5*F5 -> 880 | H5: =G5*C5 -> 52800
A6: Project Manager | B6: You or contractor | C6: 60 | D6: 220 | E6: 4 | F6: 0.75 | G6: =D6*E6*F6 -> 660 | H6: =G6*C6 -> 39600
A7: Junior Designer | B7: Optional | C7: 20 | D7: 220 | E7: 8 | F7: 0.8 | G7: =D7*E7*F7 -> 1408 | H7: =G7*C7 -> 28160
A8: TOTALS | G8: =SUM(G3:G7) -> 4862 | H8: =SUM(H3:H7) -> 331760

Sheet ⚙️ Overhead Rate
A1: ⚙️ Overhead Rate Calculator
A2: ANNUAL COST SUMMARY
A3: Cost Component | B3: Annual Amount ($) | C3: Source | D3: Notes
A4: Annual Labour Cost (all team) | B4: ='👥 Team & Hours'!H8 -> 331760 | C4: 💰 Business Costs!D4:D… | D4: Sum of all team annual pay (billable hours * rate)
A5: Annual Tool Subscriptions | B5: ='💰 Business Costs'!D9 -> 2393.76 | C5: 💰 Business Costs | D5: Direct SaaS tools total
A6: Annual Indirect / Overhead Costs | B6: ='💰 Business Costs'!D23 -> 13696.2 | C6: 💰 Business Costs | D6: Transport, utilities, insurance, etc.
A7: ⭐ TOTAL ANNUAL COSTS | B7: =SUM(B4:B6) -> 347849.96
A9: BILLABLE HOURS SUMMARY
A10: Metric | B10: Value | C10: Source | D10: Notes
A11: Total Annual Billable Hours (all team) | B11: ='👥 Team & Hours'!G8 -> 4862 | C11: 👥 Team & Hours | D11: Sum of all team billable hours per year
A13: OVERHEAD RATE CALCULATION (Formula: Total Annual Costs ÷ Total Billable Hours)
A14: ⭐ Overhead Rate per Billable Hour ($) | B14: =IF(B11>0,B7/B11,0) -> 71.544624 | C14: Auto-calculated | D14: Every billable hour must recover this amount in overhead

Sheet 🔧 Service Pricing
A1: 🔧 Service Pricing — Job Costing Method
A3: 🔧 Global Profit Mark-up % (applies to all services): | D3: 0.35
A5: # | B5: Team Member / Role | C5: Hourly Rate ($) | D5: Est. Hours This Job | E5: Direct Labour ($) | F5: Direct Expenses ($) | G5: Overhead Allocated ($) | H5: Total Job Cost ($) | I5: Min. Selling Price ($)
A7: SERVICE: 1. Web Design & Development — Per website project (avg). Adjust hours per project complexity.
A8: 1 | B8: Founder / Lead Designer | C8: ='👥 Team & Hours'!C3 -> 100 | D8: 0 | E8: =C8*D8 -> 0 | F8: 0 | G8: =D8*'⚙️ Overhead Rate'!B14 -> 0
A9: 2 | B9: Developer / Coder | C9: ='👥 Team & Hours'!C4 -> 120 | D9: 20 | E9: =C9*D9 -> 2400 | F9: — | G9: =D9*'⚙️ Overhead Rate'!B14 -> 1430.8925
A10: 3 | B10: Project Manager | C10: ='👥 Team & Hours'!C6 -> 60 | D10: 0 | E10: =C10*D10 -> 0 | F10: — | G10: =D10*'⚙️ Overhead Rate'!B14 -> 0
B11: TOTALS / MIN PRICE — 1. Web Design & Development | D11: =SUM(D8:D10) -> 20 | E11: =SUM(E8:E10) -> 2400 | F11: =F8 -> 0 | G11: =SUM(G8:G10) -> 1430.8925 | H11: =E11+F11+G11 -> 3830.8925 | I11: =H11*(1+D3) -> 5171.7048
A13: SERVICE: 2. Digital Marketing — SEO — Per month retainer. Enter monthly hours spent.
A14: 1 | B14: Digital Marketing Mgr | C14: ='👥 Team & Hours'!C5 -> 60 | D14: 8 | E14: =C14*D14 -> 480 | F14: 237 | G14: =D14*'⚙️ Overhead Rate'!B14 -> 572.35699
A15: 2 | B15: Founder / Lead Designer | C15: ='👥 Team & Hours'!C3 -> 100 | D15: 0 | E15: =C15*D15 -> 0 | F15: — | G15: =D15*'⚙️ Overhead Rate'!B14 -> 0
B16: TOTALS / MIN PRICE — 2. Digital Marketing — SEO | D16: =SUM(D14:D15) -> 8 | E16: =SUM(E14:E15) -> 480 | F16: =F14 -> 237 | G16: =SUM(G14:G15) -> 572.35699 | H16: =E16+F16+G16 -> 1289.357 | I16: =H16*(1+D3) -> 1740.6319
A18: SERVICE: 3. Digital Marketing — Display & Search Ads — Campaign setup/management per month. Ad spend not included.
A19: 1 | B19: Digital Marketing Mgr | C19: ='👥 Team & Hours'!C5 -> 60 | D19: 0 | E19: =C19*D19 -> 0 | F19: 0 | G19: =D19*'⚙️ Overhead Rate'!B14 -> 0
A20: 2 | B20: Founder / Lead Designer | C20: ='👥 Team & Hours'!C3 -> 100 | D20: 0 | E20: =C20*D20 -> 0 | F20: — | G20: =D20*'⚙️ Overhead Rate'!B14 -> 0
B21: TOTALS / MIN PRICE — 3. Digital Marketing — Display & Search Ads | D21: =SUM(D19:D20) -> 0 | E21: =SUM(E19:E20) -> 0 | F21: =F19 -> 0 | G21: =SUM(G19:G20) -> 0 | H21: =E21+F21+G21 -> 0 | I21: =H21*(1+D3) -> 0
A23: SERVICE: 4. Project Management — Standalone PM service per project or monthly.
A24: 1 | B24: Project Manager | C24: ='👥 Team & Hours'!C6 -> 60 | D24: 6 | E24: =C24*D24 -> 360 | F24: 0 | G24: =D24*'⚙️ Overhead Rate'!B14 -> 429.26774
A25: 2 | B25: Founder / Lead Designer | C25: ='👥 Team & Hours'!C3 -> 100 | D25: 0 | E25: =C25*D25 -> 0 | F25: — | G25: =D25*'⚙️ Overhead Rate'!B14 -> 0
B26: TOTALS / MIN PRICE — 4. Project Management | D26: =SUM(D24:D25) -> 6 | E26: =SUM(E24:E25) -> 360 | F26: =F24 -> 0 | G26: =SUM(G24:G25) -> 429.26774 | H26: =E26+F26+G26 -> 789.26774 | I26: =H26*(1+D3) -> 1065.5115

Sheet 📊 Price Summary
A1: 📊 Price Summary — Minimum Selling Prices
A3: KEY INPUTS AT A GLANCE
A4: Overhead Rate per Billable Hour | D4: ='⚙️ Overhead Rate'!B14 -> 71.544624
A5: Total Annual Billable Hours | D5: ='⚙️ Overhead Rate'!B11 -> 4862
A6: Total Annual Business Costs | D6: ='⚙️ Overhead Rate'!B7 -> 347849.96
A7: Applied Profit Mark-up | D7: ='🔧 Service Pricing'!D3 -> 0.35
A9: SERVICE PRICE LIST
A10: # | B10: Service | C10: Est. Hours | D10: Total Job Cost ($) | E10: Min. Selling Price ($) | F10: Suggested Rate Note
A11: 1 | B11: Web Design & Development | C11: ='🔧 Service Pricing'!D11 -> 20 | D11: ='🔧 Service Pricing'!H11 -> 3830.8925 | E11: ='🔧 Service Pricing'!I11 -> 5171.7048 | F11: Per project
A12: 2 | B12: Digital Marketing — SEO | C12: ='🔧 Service Pricing'!D16 -> 8 | D12: ='🔧 Service Pricing'!H16 -> 1289.357 | E12: ='🔧 Service Pricing'!I16 -> 1740.6319 | F12: Per month retainer
A13: 3 | B13: Digital Marketing — Display & Search Ads | C13: ='🔧 Service Pricing'!D21 -> 0 | D13: ='🔧 Service Pricing'!H21 -> 0 | E13: ='🔧 Service Pricing'!I21 -> 0 | F13: Per month
A14: 4 | B14: Project Management | C14: ='🔧 Service Pricing'!D26 -> 6 | D14: ='🔧 Service Pricing'!H26 -> 789.26774 | E14: ='🔧 Service Pricing'!I26 -> 1065.5115 | F14: Per project / month
A16: 💡 These are MINIMUM prices. Always check competitor rates and market positioning before finalising.
